css_explore.py
css_explore-1.1.0.dist-info/LICENSE
css_explore-1.1.0.dist-info/METADATA
css_explore-1.1.0.dist-info/WHEEL
css_explore-1.1.0.dist-info/entry_points.txt
css_explore-1.1.0.dist-info/top_level.txt
css_explore-1.1.0.dist-info/RECORD
